cli.py
PyGitio-1.1.dist-info/METADATA
PyGitio-1.1.dist-info/RECORD
PyGitio-1.1.dist-info/WHEEL
PyGitio-1.1.dist-info/entry_points.txt
PyGitio-1.1.dist-info/top_level.txt
