Metadata-Version: 2.1
Name: PyGitio
Version: 1.1
Summary: Command line utility to quickly shorten github links with support for custom urls.
Home-page: https://github.com/hsuay/PyGitio
Author: ayush
Author-email: hsuay@outlook.com
License: MIT
Project-URL: Source, https://github.com/hsuay/PyGitio
Project-URL: Say Thanks!, https://saythanks.io/to/hsuay
Project-URL: Buy me a coffee!, http://bmc.xyz/ayush
Keywords: gitio github url shortener shrinker
Platform: any
Requires-Dist: requests
Requires-Dist: Click
Requires-Dist: pyperclip
